{
	"configurations" : 
	[
		{
			"directories" : 
			[
				{
					"build" : ".",
					"hasInstallRule" : true,
					"jsonFile" : "directory-.-416b33216217618fccf2.json",
					"minimumCMakeVersion" : 
					{
						"string" : "3.12"
					},
					"projectIndex" : 0,
					"source" : ".",
					"targetIndexes" : 
					[
						0,
						1,
						2
					]
				}
			],
			"name" : "",
			"projects" : 
			[
				{
					"directoryIndexes" : 
					[
						0
					],
					"name" : "uav_camera",
					"targetIndexes" : 
					[
						0,
						1,
						2
					]
				}
			],
			"targets" : 
			[
				{
					"directoryIndex" : 0,
					"id" : "camera_publisher::@6890427a1f51a3e7e1df",
					"jsonFile" : "target-camera_publisher-e05f3dd8d4f95e0615de.json",
					"name" : "camera_publisher",
					"projectIndex" : 0
				},
				{
					"directoryIndex" : 0,
					"id" : "uav_camera_uninstall::@6890427a1f51a3e7e1df",
					"jsonFile" : "target-uav_camera_uninstall-8fe3f277d4e7cd0186cc.json",
					"name" : "uav_camera_uninstall",
					"projectIndex" : 0
				},
				{
					"directoryIndex" : 0,
					"id" : "uninstall::@6890427a1f51a3e7e1df",
					"jsonFile" : "target-uninstall-aa9fc17e8c73d2479bbc.json",
					"name" : "uninstall",
					"projectIndex" : 0
				}
			]
		}
	],
	"kind" : "codemodel",
	"paths" : 
	{
		"build" : "/home/drone/drone_ws/build/uav_camera",
		"source" : "/home/drone/drone_ws/src/uav_camera"
	},
	"version" : 
	{
		"major" : 2,
		"minor" : 3
	}
}
